[
   {
      "Id": 1,
      "itemPrice": 10,
      "itemName": "Сік 🧃",
      "itemDescription": "Свіжовижатий виноградно яблучний сік"
   },
   {
      "Id": 2,
      "itemPrice": 20,
      "itemName": "Міні-піца 🍕",
      "itemDescription": "кетчуп, сир, куряче м'ясо"
   },
   {
      "Id": 3,
      "itemPrice": 5,
      "itemName": "Пончик 🍩",
      "itemDescription": "шоколадний"
   },
   {
      "Id": 4,
      "itemPrice": 7,
      "itemName": "Джем 🍓",
      "itemDescription": "Полуничний"
   },
   {
      "Id": 5,
      "itemPrice": 15,
      "itemName": "Морозиво 🍧",
      "itemDescription": "вершково-полуничне"
   }
]
